nebullvm/__init__.py
nebullvm/config.py
nebullvm/api/__init__.py
nebullvm/apps/__init__.py
nebullvm/apps/base.py
nebullvm/core/__init__.py
nebullvm/core/models.py
nebullvm/core/types.py
nebullvm/core/tests/__init__.py
nebullvm/core/tests/test_models.py
nebullvm/installers/__init__.py
nebullvm/installers/auto_installer.py
nebullvm/installers/install_bladedisc.sh
nebullvm/installers/install_fastertransformer.sh
nebullvm/installers/install_tensor_rt.sh
nebullvm/installers/install_tvm.sh
nebullvm/installers/install_tvm_prerequisites.sh
nebullvm/installers/installers.py
nebullvm/installers/tests/__init__.py
nebullvm/installers/tests/test_install_frameworks.py
nebullvm/installers/tvm_installers/arm/config.cmake
nebullvm/installers/tvm_installers/arm_cuda/config.cmake
nebullvm/installers/tvm_installers/x86/config.cmake
nebullvm/installers/tvm_installers/x86_cuda/config.cmake
nebullvm/operations/__init__.py
nebullvm/operations/base.py
nebullvm/operations/conversions/__init__.py
nebullvm/operations/conversions/converters.py
nebullvm/operations/conversions/huggingface.py
nebullvm/operations/conversions/pytorch.py
nebullvm/operations/conversions/tensorflow.py
nebullvm/operations/conversions/utils.py
nebullvm/operations/fetch_operations/__init__.py
nebullvm/operations/fetch_operations/local.py
nebullvm/operations/inference_learners/__init__.py
nebullvm/operations/inference_learners/base.py
nebullvm/operations/inference_learners/blade_disc.py
nebullvm/operations/inference_learners/builders.py
nebullvm/operations/inference_learners/deepsparse.py
nebullvm/operations/inference_learners/faster_transformer.py
nebullvm/operations/inference_learners/huggingface.py
nebullvm/operations/inference_learners/neural_compressor.py
nebullvm/operations/inference_learners/onnx.py
nebullvm/operations/inference_learners/openvino.py
nebullvm/operations/inference_learners/tensor_rt.py
nebullvm/operations/inference_learners/tensorflow.py
nebullvm/operations/inference_learners/torch_dynamo.py
nebullvm-0.10.0.dist-info/LICENSE
nebullvm-0.10.0.dist-info/METADATA
nebullvm-0.10.0.dist-info/WHEEL
nebullvm-0.10.0.dist-info/top_level.txt
nebullvm-0.10.0.dist-info/RECORD
