Metadata-Version: 2.1
Name: nebullvm
Version: 0.10.0
License-File: LICENSE
Requires-Dist: numpy (<1.24.0,>=1.21.0)
Requires-Dist: py-cpuinfo (>=8.0.0)
Requires-Dist: PyYAML (>=6.0)
Requires-Dist: psutil (>=5.0.0)
Requires-Dist: requests (>=2.26.0)
Requires-Dist: tqdm (>=4.36.0)
Requires-Dist: packaging (>=21.3)
Requires-Dist: loguru (>=0.5.3)
